<?xml version="1.0" encoding="ISO-8859-1"?>
<Program>
<LetCommand>
<RecursiveProcFunc>
<SequentialDeclaration>
<ProcDeclaration>
<Identifier value="printl"/>
<SingleFormalParameterSequence>/n<ConstantFormalParameters>/n<Identifier value="x"/>
<SimpleTypeDenoter>
<Identifier value="Integer"/>
</SimpleTypeDenoter>
</ConstantFormalParameters>/n</SingleFormalParameterSequence>/n<SequentialCommand>
<CallCommand>
<Identifier value="print"/>
<SingleActualParameterSequence>
<ConstantActualParameter>
<VnameExpression>
<SimpleVname>
<Identifier value="x"/>
</SimpleVname>
</VnameExpression>
</ConstantActualParameter>
</SingleActualParameterSequence>
</CallCommand>
<CallCommand>
<Identifier value="puteol"/>
<EmptyActualParameterSequence/>
</CallCommand>
</SequentialCommand>
</ProcDeclaration>
<ProcDeclaration>
<Identifier value="print"/>
<SingleFormalParameterSequence>/n<ConstantFormalParameters>/n<Identifier value="x"/>
<SimpleTypeDenoter>
<Identifier value="Integer"/>
</SimpleTypeDenoter>
</ConstantFormalParameters>/n</SingleFormalParameterSequence>/n<CallCommand>
<Identifier value="putint"/>
<SingleActualParameterSequence>
<ConstantActualParameter>
<VnameExpression>
<SimpleVname>
<Identifier value="x"/>
</SimpleVname>
</VnameExpression>
</ConstantActualParameter>
</SingleActualParameterSequence>
</CallCommand>
</ProcDeclaration>
</SequentialDeclaration>
</RecursiveProcFunc>
<CallCommand>
<Identifier value="printl"/>
<SingleActualParameterSequence>
<ConstantActualParameter>
<IntegerExpression>
<IntegerLiteral value="1"/>
</IntegerExpression>
</ConstantActualParameter>
</SingleActualParameterSequence>
</CallCommand>
</LetCommand>
</Program>
